{"en":{"atmosphere":"Suburban Tobu station, quiet outside rush hour. Industrial patches, residential sprawl, low-rise feel.","landmarks":"Green parks dominate (2.9M sqm). Few named attractions, mostly nature walks.","food":"Handful of casual spots scattered nearby. Data limited for this outlying town.","nightlife":"Minimal. Last train 23:58, locals move elsewhere for evening."},"ja":{"atmosphere":"東武駅、朝夕以外は静か。工業地帯と住宅地の混在、低層建築。","landmarks":"広大な公園（290万平米）。名所は少ない、自然散策が主。","food":"数軒の飲食店。この周辺はデータ限定。","nightlife":"ほぼ皆無。終電23:58。"},"ru":{"atmosphere":"Жилая пригородная станция Tobu. Молчаливая днём, оживает на час-два. Промзоны, коттеджи, сельская периферия.","landmarks":"Паркан (2.9М кв.м) покрывает весь район. Туристических достопримечательностей нет.","food":"Несколько кафе в пешеходном радиусе. Нет разнообразия, как во всех пригородах.","nightlife":"Практически нет. Дневной commuter hub, вечеров нет."}}