{"en":{"atmosphere":"Green Line bedroom, 52 min. Tsuzuki ward, cheap, suburban, high seismic.","landmarks":"None. Built-up residential, no identity.","food":"Minimal.","nightlife":"Minimal."},"ja":{"atmosphere":"グリーンライン寝室、52分。都筑区、安い、郊外的、地震リスク高。","landmarks":"なし。建て詰まった住宅地、無個性。","food":"ほぼなし。","nightlife":"ほぼなし。"},"ru":{"atmosphere":"Green Line спальня, 52 мин. Раньон Цудзуки, дёшево, пригород, высокий сейсм.","landmarks":"Нет. Застроенный жилой район без лица.","food":"Минимально.","nightlife":"Минимально."}}
