{
  "en": {
    "atmosphere": "Enoshima beach suburb, Odakyu coastal. Low vibe, 16k daily. Seaside charm, quiet. 76 min from center.",
    "landmarks": "Enoshima ferry, beach promenade, summer crowd magnet. Surf culture vibes. Pedestrian-friendly (11 streets).",
    "food": "26 listings (7 izakaya), 6 cafes, 9. Modest seaside scene. Summer lift, winter slack.",
    "nightlife": "Minimal (1 midnight spot). Beach town closes early."
  },
  "ja": {
    "atmosphere": "江ノ島ビーチ郊外、小田急海岸線。低い派手さ、1日1万6千人。海辺の魅力、静か。中心から76分。",
    "landmarks": "江ノ島フェリー、ビーチプロムナード、夏は混雑。サーフ文化。歩行者フレンドリー（11通り）。",
    "food": "ホットペッパー26軒（居酒屋7軒）、カフェ6軒、9軒。控えめなビーチシーン。夏は盛況、冬は静か。",
    "nightlife": "ほぼなし（深夜営業1軒）。ビーチタウン早仕舞い。"
  },
  "ru": {
    "atmosphere": "Пригород пляжа Эношима, Odakyu побережье. Низкий шик, 16k ежедневно. Приморское очарование, тишина. 76 минут от центра.",
    "landmarks": "Паром Эношима, пляжный променад, летний магнит толпы. Серфовая культура. Пешеходные 11 улиц.",
    "food": "26 listings (7 изакая), 6 кафе, 9. Скромная приморская сцена. Летний подъём, зимний спад.",
    "nightlife": "Минимум (1 полуночное место). Пляжный город закрывает рано."
  }
}