{
  "en": {
    "atmosphere": "Meguro-line shotengai pocket, compact and livable. Safe, pricey, soft-ground flag despite the hill.",
    "landmarks": "Nishi-Koyama shopping street, Musashi-Koyama spillover, small Meguro-line lanes.",
    "food": "131 restaurants, 44 izakayas, 13 bars. Strong local eating, small-room drinking.",
    "nightlife": "55 late spots, one tiny club, no karaoke. Local bars, not a big night."
  },
  "ja": {
    "atmosphere": "目黒線沿いの商店街ポケット、コンパクトで住みやすい。安全だが高め、地盤リスクあり。",
    "landmarks": "西小山商店街、武蔵小山のこぼれ、小さな目黒線の路地。",
    "food": "飲食131軒、居酒屋44軒、バー13軒。地元飯は強い、小箱飲みもある。",
    "nightlife": "深夜営業55軒、小さなクラブ1軒、カラオケなし。地元バー中心、大夜遊びではない。"
  },
  "ru": {
    "atmosphere": "Карман shotengai на Meguro Line, компактно и удобно. Безопасно, дорого, есть soft-ground флаг.",
    "landmarks": "Nishi-Koyama shopping street, перелив Musashi-Koyama, малые переулки Meguro Line.",
    "food": "131 ресторан, 44 изакая, 13 баров. Сильная локальная еда, выпивка в малых комнатах.",
    "nightlife": "55 поздних мест, один крошечный клуб, без караоке. Локальные бары, не большая ночь."
  }
}
