{"en":{"atmosphere":"Yokohama Blue Line satellite, 50 minutes out. Quiet residential, sporadic nightlife, forests nearby.","landmarks":"Omotesando strip, sports grounds, 1M sqm Shinrin parks. Nature-first urbanism.","food":"20 restaurants, 7 izakayas — modest. Daytime lunch zones, evenings empty.","nightlife":"4 late-night spots, minimal. Neighborhood bars, no clubs. Early close."},"ja":{"atmosphere":"横浜ブルーライン沿線。50分圏。静かな住宅地。森が隣接。","landmarks":"表参道、スポーツグラウンド、100万ヘクタール級の公園。緑優先設計。","food":"飲食店20軒、居酒屋7軒。昼営業が主。夜は人気ない。","nightlife":"夜営業4軒のみ。近所の飲み屋。クラブなし。早仕舞い。"},"ru":{"atmosphere":"Спутник Йокогамской синей линии, 50 минут. Тихое, спортивное, леса рядом.","landmarks":"Омотесандо, спортгрунды, 100М кв км парков. Зелень в приоритете.","food":"20 ресторанов, 7 изакаи. Скромно. Обедают днём, пусто вечером.","nightlife":"4 ночных места всего. Соседский уровень. Ночи короткие."}}
