{"en":{"atmosphere":"Residential Koto ward near Odaiba. Quiet, safe, but food and vibe lag. Young professionals escaping central rents.","landmarks":"Pedestrian streets (43!), cultural venue. Riverfront development. Inland version of Odaiba calm.","food":"3 restaurants, 1 izakaya. Bare minimum. Convenience store default.","nightlife":"Minimal. Office crowd clears by 10pm."},"ja":{"atmosphere":"江東区の江戸川沿い。静か、安全だが食事と雰囲気は物足りない。中心部の家賃から逃げた若手。","landmarks":"歩行者街43本！1つの文化施設。川沿い開発。内陸版お台場の静けさ。","food":"レストラン3軒、居酒屋1軒。最低限。コンビニがデフォルト。","nightlife":"ほぼなし。サラリーマンは夜10時に消える。"},"ru":{"atmosphere":"Жилой район Кото близ Одайбы. Тихо, безопасно, но еда и атмосфера отстают. Молодые профессионалы спасаются от центральных арендов.","landmarks":"Пешеходные улицы (43!), культурное заведение. Развитие вдоль реки. Внутриземельная версия тишины Одайбы.","food":"3 ресторана, 1 изакая. Минимум. Удобство по умолчанию.","nightlife":"Минимально. Офисная толпа уходит к 22:00."}}
