{"en": {"atmosphere": "Saitama museum stop, family-day anchor. New Shuttle single-track, suburban sprawl.", "landmarks": "Railway Museum, Omiya station nexus. Museum-only destination.", "food": "Museum cafe food. No neighborhood restaurants.", "nightlife": "Minimal. Daytrip spot only."}, "ja": {"atmosphere": "埼玉の博物館駅、家族連れ向け。ニューシャトル一本、郊外スプロール。", "landmarks": "鉄道博物館、大宮駅に隣接。博物館メインの目的地。", "food": "博物館カフェのみ。周辺飲食店なし。", "nightlife": "ほぼ無し。日帰り地。"}, "ru": {"atmosphere": "Станция музея в Сайтаме, якорь для семейных дней. Однопутная линия New Shuttle, пригородная спрол.", "landmarks": "Железнодорожный музей, узел Омии. Только туристическая точка.", "food": "Кафе музея. Никаких ресторанов по соседству.", "nightlife": "Минимально. Только дневной турист-стоп."}}
